mantis_xray/Mantis_batch_settings.txt
mantis_xray/Mrc.py
mantis_xray/__init__.py
mantis_xray/__main__.py
mantis_xray/analyze.py
mantis_xray/data_stack.py
mantis_xray/data_struct.py
mantis_xray/dialogalign.ui
mantis_xray/dialogsave.ui
mantis_xray/helpers.py
mantis_xray/henke.py
mantis_xray/henke.xdr
mantis_xray/logos.py
mantis_xray/mantis.py
mantis_xray/mantis_qt.py
mantis_xray/nnma.py
mantis_xray/pageloaddata.ui
mantis_xray/pagemap.ui
mantis_xray/pagestack.ui
mantis_xray/showalign2.ui
mantis_xray/showartefacts.ui
mantis_xray/showmulticrop.ui
mantis_xray/showodmap.ui
mantis_xray/showspectralroi.ui
mantis_xray/stylesheet_global.qss
mantis_xray/tomo_reconstruction.py
mantis_xray/TomoCS/__init__.py
mantis_xray/TomoCS/_rank_order.py
mantis_xray/TomoCS/forward_backward_tv.py
mantis_xray/TomoCS/projections.py
mantis_xray/TomoCS/sirt.py
mantis_xray/TomoCS/tv_denoising.py
mantis_xray/TomoCS/util.py
mantis_xray/file_plugins/__init__.py
mantis_xray/file_plugins/file_bim.py
mantis_xray/file_plugins/file_csv.py
mantis_xray/file_plugins/file_dataexch_hdf5.py
mantis_xray/file_plugins/file_json.py
mantis_xray/file_plugins/file_ncb.py
mantis_xray/file_plugins/file_nexus_hdf5.py
mantis_xray/file_plugins/file_sdf.py
mantis_xray/file_plugins/file_sm_netcdf.py
mantis_xray/file_plugins/file_stk.py
mantis_xray/file_plugins/file_tif.py
mantis_xray/file_plugins/file_xrm.py
mantis_xray/images/Mantis_logo.icns
mantis_xray/images/Mantis_logo.ico
mantis_xray/images/Mantis_logo_about.png
mantis_xray/images/document-open.png
mantis_xray/images/help-browser.png
mantis_xray/images/logo-2l-32.ico
mantis_xray/images/media-floppy.png
mantis_xray/images/mirror.png
mantis_xray/images/open-sl.png
mantis_xray/images/rotate.png
mantis_xray-3.2.9.dist-info/LICENSE
mantis_xray-3.2.9.dist-info/METADATA
mantis_xray-3.2.9.dist-info/WHEEL
mantis_xray-3.2.9.dist-info/entry_points.txt
mantis_xray-3.2.9.dist-info/top_level.txt
mantis_xray-3.2.9.dist-info/RECORD
