Metadata-Version: 2.1
Name: mantis-xray
Version: 3.2.9
Summary: MANTiS is a Multivariate ANalysis Tool for x-ray Spectromicroscopy
Home-page: https://spectromicroscopy.com/
Author: Mirna Lerotic
Author-email: mirna@2ndlookconsulting.com
Project-URL: Code, https://github.com/mlerotic/spectromicroscopy
Project-URL: Documentation, https://docs.spectromicroscopy.com
Classifier: Programming Language :: Python :: 3
Classifier: License :: OSI Approved :: GNU General Public License v3 or later (GPLv3+)
Classifier: Operating System :: OS Independent
Classifier: Topic :: Scientific/Engineering
Requires-Python: >=3
License-File: LICENSE
Requires-Dist: PyQt5>=5.15.9
Requires-Dist: numpy
Requires-Dist: scipy>=1.11.4
Requires-Dist: matplotlib>=3.6.0
Requires-Dist: h5py
Requires-Dist: Pillow
Requires-Dist: lxml
Requires-Dist: pyqtgraph>=0.13.7
Requires-Dist: scikit-image>=0.19.1
Provides-Extra: netcdf
Requires-Dist: netcdf4-python; extra == "netcdf"
